dqrobotics/interfaces/vrep/__init__.py
dqrobotics/interfaces/vrep/_core.cpython-312-darwin.so
dqrobotics_interface_coppeliasim_vrep-0.25.6.4.dist-info/licenses/LICENSE
dqrobotics_interface_coppeliasim_vrep-0.25.6.4.dist-info/METADATA
dqrobotics_interface_coppeliasim_vrep-0.25.6.4.dist-info/WHEEL
dqrobotics_interface_coppeliasim_vrep-0.25.6.4.dist-info/top_level.txt
dqrobotics_interface_coppeliasim_vrep-0.25.6.4.dist-info/RECORD
